pitchscapes/__init__.py
pitchscapes/keyfinding.py
pitchscapes/model.py
pitchscapes/optimization.py
pitchscapes/plotting.py
pitchscapes/reader.py
pitchscapes/scapes.py
pitchscapes/util.py
pitchscapes-0.2.0.dist-info/LICENSE
pitchscapes-0.2.0.dist-info/METADATA
pitchscapes-0.2.0.dist-info/WHEEL
pitchscapes-0.2.0.dist-info/top_level.txt
pitchscapes-0.2.0.dist-info/RECORD
