Metadata-Version: 2.2
Name: pitchscapes
Version: 0.2.0
Summary: computing pitch-scapes and pitch-scape clusters
Home-page: https://github.com/robert-lieck/pitchscapes
Author: Robert Lieck
Author-email: robert.lieck@durham.ac.uk
Classifier: Programming Language :: Python :: 3
Classifier: License :: OSI Approved :: GNU General Public License v3 (GPLv3)
Classifier: Operating System :: OS Independent
Requires-Python: >=3.6
License-File: LICENSE
Requires-Dist: numpy
Requires-Dist: matplotlib
Requires-Dist: torch
Requires-Dist: scipy
Requires-Dist: mido
Requires-Dist: IPython
Requires-Dist: music21
Dynamic: author
Dynamic: author-email
Dynamic: classifier
Dynamic: description
Dynamic: description-content-type
Dynamic: home-page
Dynamic: requires-dist
Dynamic: requires-python
Dynamic: summary
